hexgpc/__init__.py
hexgpc-1.1.1.dist-info/METADATA
hexgpc-1.1.1.dist-info/WHEEL
hexgpc-1.1.1.dist-info/top_level.txt
hexgpc-1.1.1.dist-info/RECORD
